{
  "taskID": "rework-35",
  "type": "rework",
  "status": "running",
  "projectName": "social-world",
  "startedAt": "2026-04-26T15:20:19.765417+08:00",
  "lastHeartbeat": "2026-04-26T15:49:26.117393+08:00",
  "stepResults": {
    "addLabel": {
      "status": "success",
      "exitCode": 1
    },
    "addPRComment": {
      "status": "success",
      "exitCode": 1
    },
    "checkEmulator": {
      "status": "success",
      "exitCode": 0
    },
    "ensureCommitAndPush": {
      "status": "success",
      "exitCode": 0
    },
    "fetchOrigin": {
      "status": "success",
      "exitCode": 0
    },
    "flutterDoctor": {
      "status": "success",
      "exitCode": 0
    },
    "installDeps": {
      "status": "success",
      "exitCode": 0
    },
    "preCommitChecks": {
      "status": "success",
      "exitCode": 0
    },
    "runAgent": {
      "status": "success",
      "exitCode": 0
    }
  }
}